aws_infrastructure_sdk/__init__.py
aws_infrastructure_sdk/cloud_formation/__init__.py
aws_infrastructure_sdk/cloud_formation/availability_zones.py
aws_infrastructure_sdk/cloud_formation/types.py
aws_infrastructure_sdk/cloud_formation/fargate_ci_cd/__init__.py
aws_infrastructure_sdk/cloud_formation/fargate_ci_cd/ecs_autoscaling.py
aws_infrastructure_sdk/cloud_formation/fargate_ci_cd/ecs_loadbalancer.py
aws_infrastructure_sdk/cloud_formation/fargate_ci_cd/ecs_main.py
aws_infrastructure_sdk/cloud_formation/fargate_ci_cd/ecs_pipeline.py
aws_infrastructure_sdk/cloud_formation/fargate_ci_cd/main.py
aws_infrastructure_sdk/cloud_formation/lambda_ci_cd/__init__.py
aws_infrastructure_sdk/cloud_formation/lambda_ci_cd/deployment.template
aws_infrastructure_sdk/cloud_formation/lambda_ci_cd/deployment_lambda.py
aws_infrastructure_sdk/cloud_formation/lambda_ci_cd/lambda_pipeline.py
aws_infrastructure_sdk/cloud_formation/lambda_ci_cd/main.py
aws_infrastructure_sdk/cloud_formation/lambda_ci_cd/python-buildspec.yml
aws_infrastructure_sdk/cloud_formation/stack/__init__.py
aws_infrastructure_sdk/cloud_formation/stack/abstract_stack_action.py
aws_infrastructure_sdk/cloud_formation/stack/api_gateway_describer.py
aws_infrastructure_sdk/cloud_formation/stack/resource_describer.py
aws_infrastructure_sdk/cloud_formation/stack/stack_deleter.py
aws_infrastructure_sdk/cloud_formation/stack/stack_deployer.py
aws_infrastructure_sdk/cloud_formation/stack/stack_status.py
aws_infrastructure_sdk/s3/__init__.py
aws_infrastructure_sdk/s3/s3_abstract_action.py
aws_infrastructure_sdk/s3/s3_bucket_checker.py
aws_infrastructure_sdk/s3/s3_bucket_creator.py
aws_infrastructure_sdk/s3/s3_bucket_deleter.py
aws_infrastructure_sdk/s3/s3_uploader.py
aws_infrastructure_sdk/zappa/__init__.py
aws_infrastructure_sdk/zappa/utils.py
aws_infrastructure_sdk/zappa/zappa_config.py
aws_infrastructure_sdk/zappa/zappa_deployer.py
aws_infrastructure_sdk/zappa/zappa_django_deploy.py
aws_infrastructure_sdk-2.1.0.dist-info/LICENSE.txt
aws_infrastructure_sdk-2.1.0.dist-info/METADATA
aws_infrastructure_sdk-2.1.0.dist-info/WHEEL
aws_infrastructure_sdk-2.1.0.dist-info/top_level.txt
aws_infrastructure_sdk-2.1.0.dist-info/RECORD
