Metadata-Version: 2.1
Name: aws-infrastructure-sdk
Version: 2.1.0
Summary: SDK that helps to build AWS - CloudFormation infrastructure projects.
Home-page: https://github.com/laimonassutkus/AwsInfrastructureSdk
Author: Laimonas Sutkus
Author-email: laimonas.sutkus@gmail.com
License: GNU GENERAL PUBLIC LICENSE Version 3
Keywords: AWS SDK CloudFormation Zappa Infrastructure Cloud
Platform: UNKNOWN
Classifier: Programming Language :: Python :: 3
Classifier: Programming Language :: Python :: 3.5
Classifier: Programming Language :: Python :: 3.6
Classifier: Operating System :: OS Independent
Requires-Dist: boto3
Requires-Dist: botocore
Requires-Dist: troposphere
Requires-Dist: cfnresponse
Requires-Dist: aws-cf-custom-resources
Requires-Dist: aws-lambda
